rickdex/__init__.py
rickdex/rickdex.py
rickdex-0.3.1.dist-info/METADATA
rickdex-0.3.1.dist-info/WHEEL
rickdex-0.3.1.dist-info/top_level.txt
rickdex-0.3.1.dist-info/RECORD
