Metadata-Version: 2.4
Name: rickdex
Version: 0.3.1
Summary: Uma biblioteca Python para interagir com a API Rick and Morty.
Author-email: Vitor <vitorlins485@gmail.com>
Classifier: Programming Language :: Python :: 3
Classifier: License :: OSI Approved :: MIT License
Classifier: Operating System :: OS Independent
Requires-Python: >=3.8
Requires-Dist: requests
